Metadata-Version: 1.1
Name: digimat.dyndcf
Version: 0.0.2
Summary: Digimat Dynamic DCF API Wrapper
Home-page: https://www.digimat.ch
Author: Frederic Hess
Author-email: fhess@st-sa.ch
License: PSF
Platform: UNKNOWN
Classifier: Development Status :: 4 - Beta
Classifier: Programming Language :: Python :: 3
